metrics/__init__.py
metrics/_bleu.py
metrics/_rouge.py
nlp_metrics-0.2.0.dist-info/LICENSE
nlp_metrics-0.2.0.dist-info/METADATA
nlp_metrics-0.2.0.dist-info/WHEEL
nlp_metrics-0.2.0.dist-info/top_level.txt
nlp_metrics-0.2.0.dist-info/RECORD
