Metadata-Version: 2.1
Name: nlp-metrics
Version: 0.2.0
Summary: A package of RL algorithms
Home-page: https://github.com/leoxiang66/nlp_metrics
Author: Tao Xiang
Author-email: tao.xiang@tum.de
Classifier: Programming Language :: Python :: 3
Classifier: License :: OSI Approved :: MIT License
License-File: LICENSE
